twissreader/__init__.py
twissreader/twissreader_csv.py
twissreader/twissreader_obj.py
twissreader/twissreader_tfs.py
twissreader/twissreader_twiss.py
twissreader-0.1.0.dist-info/LICENSE
twissreader-0.1.0.dist-info/METADATA
twissreader-0.1.0.dist-info/WHEEL
twissreader-0.1.0.dist-info/top_level.txt
twissreader-0.1.0.dist-info/RECORD
