Metadata-Version: 2.1
Name: twissreader
Version: 0.1.0
Summary: Reading Twiss-files created by MAD-X
Home-page: https://gitlab.cern.ch/cstaufen/twissreader
Author: Christian Staufenbiel
Author-email: christian.staufenbiel@cern.ch
License: UNKNOWN
Platform: UNKNOWN
Classifier: Programming Language :: Python :: 3
Classifier: License :: OSI Approved :: MIT License
Classifier: Operating System :: OS Independent
